OBSV/Calculator.py
OBSV/Molecule.py
OBSV/Results.py
OBSV/Strain_energy.py
OBSV/__init__.py
OBSV/basis_functions.py
OBSV/fragmentation.py
OBSV/inputs.py
OBSV/lib/ONIOM_Cscale.txt
OBSV/lib/ONIOM_Hscale.txt
OBSV/lib/ONIOM_Nscale.txt
OBSV/lib/ONIOM_Oscale.txt
OBSV-1.0.4.dist-info/METADATA
OBSV-1.0.4.dist-info/WHEEL
OBSV-1.0.4.dist-info/entry_points.txt
OBSV-1.0.4.dist-info/top_level.txt
OBSV-1.0.4.dist-info/RECORD
