Metadata-Version: 2.1
Name: OBSV
Version: 1.0.4
Summary: ONIOM-based Strain Visualisation
Home-page: 
Author-email: yanzy@sustech.edu.cn
Requires-Python: ~=3.9
